{
  "applications": ["resume"],
  "changelogDate": "20240308075405",
  "dto": "no",
  "embedded": false,
  "entityTableName": "personal_details",
  "fields": [
    {
      "fieldName": "profilePhoto",
      "fieldType": "byte[]",
      "fieldTypeBlobContent": "any"
    },
    {
      "fieldName": "firstName",
      "fieldType": "String",
      "fieldValidateRules": ["required"]
    },
    {
      "fieldName": "lastName",
      "fieldType": "String",
      "fieldValidateRules": ["required"]
    },
    {
      "fieldName": "email",
      "fieldType": "String",
      "fieldValidateRules": ["required"]
    },
    {
      "fieldName": "phone",
      "fieldType": "String"
    },
    {
      "fieldName": "address",
      "fieldType": "String"
    },
    {
      "fieldName": "city",
      "fieldType": "String"
    },
    {
      "fieldName": "state",
      "fieldType": "String"
    },
    {
      "fieldName": "zipCode",
      "fieldType": "String"
    },
    {
      "fieldName": "country",
      "fieldType": "String"
    }
  ],
  "fluentMethods": true,
  "jpaMetamodelFiltering": false,
  "name": "PersonalDetails",
  "pagination": "no",
  "readOnly": false,
  "relationships": [],
  "service": "no"
}
